{"icon":"fa-flag","label":"Locale","description":"Locale","core":true,"application":true,"storage_type":["0d9f2532-aaaa-4a42-a7c0-30ffe398a4b8"],"object_fields":[{"recid":1,"label":"Name","key":false,"id":1,"name":"name","column":"50","datatype":{"id":"0c408fba-4224-4426-a0fc-0b7553c6b0ca","properties":{"width":"","require":false,"default":"","multi_lingualization":false}},"caption":true,"description":"Locale Name"},{"recid":2,"label":"Label","key":false,"id":2,"name":"label","column":"200","datatype":{"id":"0c408fba-4224-4426-a0fc-0b7553c6b0ca","properties":{"width":"","require":false,"default":"","multi_lingualization":true}},"caption":true,"description":"Label"}],"id":"917b793a-c1a9-4736-84ff-3e10c6e4a95f"}