{"name":"Text","label":"Text","require_path":"core\/Control\/Field\/Text","properties":[{"recid":1,"label":"Width","key":false,"id":1,"name":"width","column":"","datatype":{"id":"0c408fba-4224-4426-a0fc-0b7553c6b0ca","properties":{}},"caption":false,"description":"Text box width."},{"recid":2,"label":"Rrequire","key":false,"id":2,"name":"require","column":"","datatype":{"id":"970944f3-da1c-4758-b929-af35dd9be4f7","properties":{}},"caption":false,"description":"If value must be set, check this property."},{"recid":3,"label":"Default Value","key":false,"id":3,"name":"default","column":"","datatype":{"id":"0c408fba-4224-4426-a0fc-0b7553c6b0ca","properties":{}},"caption":false,"description":"Set default value."},{"recid":4,"label":"Multi Lingualization","key":false,"id":4,"name":"multi_lingualization","column":"","datatype":{"id":"970944f3-da1c-4758-b929-af35dd9be4f7","properties":null},"caption":false,"description":"Multi Lingualization"}],"id":"0c408fba-4224-4426-a0fc-0b7553c6b0ca"}